{
  "_ga_GNKQCZPK8D": {
    "visit_id": 1,
    "name": "_ga_GNKQCZPK8D",
    "domain": ".365animali.com",
    "path": "/",
    "first_party_domain": "",
    "label": 0,
    "cmp_origin": 0,
    "variable_data": [
      {
        "value": "GS1.1.1704856372.1.0.1704856372.0.0.0",
        "expiry": 1739416372,
        "session": false,
        "http_only": false,
        "host_only": true,
        "secure": false,
        "same_site": "no_restriction"
      }
    ]
  },
  "_ga_WMJPMEZ4BD": {
    "visit_id": 1,
    "name": "_ga_WMJPMEZ4BD",
    "domain": ".365animali.com",
    "path": "/",
    "first_party_domain": "",
    "label": 0,
    "cmp_origin": 0,
    "variable_data": [
      {
        "value": "GS1.1.1704856372.1.0.1704856372.0.0.0",
        "expiry": 1739416372,
        "session": false,
        "http_only": false,
        "host_only": true,
        "secure": false,
        "same_site": "no_restriction"
      }
    ]
  },
  "_ga": {
    "visit_id": 1,
    "name": "_ga",
    "domain": ".365animali.com",
    "path": "/",
    "first_party_domain": "",
    "label": 0,
    "cmp_origin": 0,
    "variable_data": [
      {
        "value": "GA1.2.2125154929.1704856372",
        "expiry": 1739416372,
        "session": false,
        "http_only": false,
        "host_only": true,
        "secure": false,
        "same_site": "no_restriction"
      }
    ]
  },
  "_gid": {
    "visit_id": 1,
    "name": "_gid",
    "domain": ".365animali.com",
    "path": "/",
    "first_party_domain": "",
    "label": 0,
    "cmp_origin": 0,
    "variable_data": [
      {
        "value": "GA1.2.35293005.1704856373",
        "expiry": 1704942772,
        "session": false,
        "http_only": false,
        "host_only": true,
        "secure": false,
        "same_site": "no_restriction"
      }
    ]
  },
  "_gat_gtag_UA_211731478_2": {
    "visit_id": 1,
    "name": "_gat_gtag_UA_211731478_2",
    "domain": ".365animali.com",
    "path": "/",
    "first_party_domain": "",
    "label": 0,
    "cmp_origin": 0,
    "variable_data": [
      {
        "value": "1",
        "expiry": 1704856432,
        "session": false,
        "http_only": false,
        "host_only": true,
        "secure": false,
        "same_site": "no_restriction"
      }
    ]
  },
  "_iub_cs-48438395-granular": {
    "visit_id": 1,
    "name": "_iub_cs-48438395-granular",
    "domain": ".365animali.com",
    "path": "/",
    "first_party_domain": "",
    "label": 0,
    "cmp_origin": 0,
    "variable_data": [
      {
        "value": "%7B%22gac%22%3A%22MX4%3D%22%7D",
        "expiry": 1736392375,
        "session": false,
        "http_only": false,
        "host_only": true,
        "secure": true,
        "same_site": "no_restriction"
      }
    ]
  },
  "euconsent-v2": {
    "visit_id": 1,
    "name": "euconsent-v2",
    "domain": ".365animali.com",
    "path": "/",
    "first_party_domain": "",
    "label": 0,
    "cmp_origin": 0,
    "variable_data": [
      {
        "value": "CP4KqwAP4KqwAB7E7CITDgCgAAAAAAAAAAAAAABBQgIgA4AM-AjwBKoCZwG-AO2AdyBBQCRAElAJRgS0AmOBMkCaQQUAAAAA",
        "expiry": 1735960375,
        "session": false,
        "http_only": false,
        "host_only": true,
        "secure": true,
        "same_site": "no_restriction"
      }
    ]
  },
  "_iub_cs-48438395": {
    "visit_id": 1,
    "name": "_iub_cs-48438395",
    "domain": ".365animali.com",
    "path": "/",
    "first_party_domain": "",
    "label": 0,
    "cmp_origin": 0,
    "variable_data": [
      {
        "value": "%7B%22timestamp%22%3A%222024-01-10T03%3A12%3A55.057Z%22%2C%22version%22%3A%221.53.2%22%2C%22consent%22%3Afalse%2C%22id%22%3A48438395%2C%22cons%22%3A%7B%22rand%22%3A%2274fd0f%22%7D%7D",
        "expiry": 1736392375,
        "session": false,
        "http_only": false,
        "host_only": true,
        "secure": true,
        "same_site": "no_restriction"
      }
    ]
  },
  "lotame_domain_check": {
    "visit_id": 1,
    "name": "lotame_domain_check",
    "domain": ".365animali.com",
    "path": "/",
    "first_party_domain": "",
    "label": 0,
    "cmp_origin": 0,
    "variable_data": [
      {
        "value": "365animali.com",
        "expiry": 1704856385,
        "session": false,
        "http_only": false,
        "host_only": true,
        "secure": false,
        "same_site": "lax"
      }
    ]
  },
  "panoramaId_expiry": {
    "visit_id": 1,
    "name": "panoramaId_expiry",
    "domain": ".365animali.com",
    "path": "/",
    "first_party_domain": "",
    "label": 0,
    "cmp_origin": 0,
    "variable_data": [
      {
        "value": "1704942775790",
        "expiry": 1704942776,
        "session": false,
        "http_only": false,
        "host_only": true,
        "secure": false,
        "same_site": "lax"
      }
    ]
  },
  "UID": {
    "visit_id": 1,
    "name": "UID",
    "domain": ".ads.stickyadstv.com",
    "path": "/",
    "first_party_domain": "",
    "label": 0,
    "cmp_origin": 0,
    "variable_data": [
      {
        "value": "a2f739a69f8041f924587b69487ec2e",
        "expiry": 1707448378,
        "session": false,
        "http_only": false,
        "host_only": true,
        "secure": true,
        "same_site": "no_restriction"
      }
    ]
  },
  "ad_simply_viewer": {
    "visit_id": 1,
    "name": "ad_simply_viewer",
    "domain": ".4wnetwork.com",
    "path": "/",
    "first_party_domain": "",
    "label": 0,
    "cmp_origin": 0,
    "variable_data": [
      {
        "value": "659e0b3bb3c5d1.11876618",
        "expiry": 1707448379,
        "session": false,
        "http_only": false,
        "host_only": true,
        "secure": true,
        "same_site": "no_restriction"
      }
    ]
  },
  "profiler": {
    "visit_id": 1,
    "name": "profiler",
    "domain": ".4wnetwork.com",
    "path": "/",
    "first_party_domain": "",
    "label": 0,
    "cmp_origin": 0,
    "variable_data": [
      {
        "value": "eyJjYW4iOnRydWUsImNvbnNlbnQiOnRydWV9",
        "expiry": 1707448379,
        "session": false,
        "http_only": false,
        "host_only": true,
        "secure": true,
        "same_site": "no_restriction"
      }
    ]
  },
  "simply_new_fc": {
    "visit_id": 1,
    "name": "simply_new_fc",
    "domain": ".4wnetwork.com",
    "path": "/",
    "first_party_domain": "",
    "label": 0,
    "cmp_origin": 0,
    "variable_data": [
      {
        "value": "%7B%22campaigns%22%3A%7B%2240614%22%3A1%7D%7D",
        "expiry": 1704927599,
        "session": false,
        "http_only": false,
        "host_only": true,
        "secure": true,
        "same_site": "no_restriction"
      }
    ]
  },
  "C": {
    "visit_id": 1,
    "name": "C",
    "domain": ".adform.net",
    "path": "/",
    "first_party_domain": "",
    "label": 0,
    "cmp_origin": 0,
    "variable_data": [
      {
        "value": "1",
        "expiry": 1707534780,
        "session": false,
        "http_only": false,
        "host_only": true,
        "secure": true,
        "same_site": "no_restriction"
      }
    ]
  },
  "uid": {
    "visit_id": 1,
    "name": "uid",
    "domain": ".adform.net",
    "path": "/",
    "first_party_domain": "",
    "label": 0,
    "cmp_origin": 0,
    "variable_data": [
      {
        "value": "4732152227980555747",
        "expiry": 1710040380,
        "session": false,
        "http_only": false,
        "host_only": true,
        "secure": true,
        "same_site": "no_restriction"
      }
    ]
  },
  "tuuid": {
    "visit_id": 1,
    "name": "tuuid",
    "domain": ".360yield.com",
    "path": "/",
    "first_party_domain": "",
    "label": 0,
    "cmp_origin": 0,
    "variable_data": [
      {
        "value": "aeea9526-7b98-4d37-a725-4aa12fdac191",
        "expiry": 1712632380,
        "session": false,
        "http_only": false,
        "host_only": true,
        "secure": true,
        "same_site": "no_restriction"
      }
    ]
  },
  "tuuid_lu": {
    "visit_id": 1,
    "name": "tuuid_lu",
    "domain": ".360yield.com",
    "path": "/",
    "first_party_domain": "",
    "label": 0,
    "cmp_origin": 0,
    "variable_data": [
      {
        "value": "1704856380",
        "expiry": 1712632380,
        "session": false,
        "http_only": false,
        "host_only": true,
        "secure": true,
        "same_site": "no_restriction"
      }
    ]
  },
  "IDE": {
    "visit_id": 1,
    "name": "IDE",
    "domain": ".doubleclick.net",
    "path": "/",
    "first_party_domain": "",
    "label": 0,
    "cmp_origin": 0,
    "variable_data": [
      {
        "value": "AHWqTUlRmccYvlE7cTIGmKlknpSm76PBDS7_hm9yPqWoQ30X99_sk9KayROojB4HIJ8",
        "expiry": 1738552381,
        "session": false,
        "http_only": true,
        "host_only": true,
        "secure": true,
        "same_site": "no_restriction"
      }
    ]
  }
}