{
  "cookielawinfo-checkbox-necessary": {
    "visit_id": 1,
    "name": "cookielawinfo-checkbox-necessary",
    "domain": "aslbi.piemonte.it",
    "path": "/",
    "first_party_domain": "",
    "label": 0,
    "cmp_origin": 0,
    "variable_data": [
      {
        "value": "yes",
        "expiry": 1736500985,
        "session": false,
        "http_only": false,
        "host_only": true,
        "secure": false,
        "same_site": "no_restriction"
      }
    ]
  },
  "cookielawinfo-checkbox-performance": {
    "visit_id": 1,
    "name": "cookielawinfo-checkbox-performance",
    "domain": "aslbi.piemonte.it",
    "path": "/",
    "first_party_domain": "",
    "label": 0,
    "cmp_origin": 0,
    "variable_data": [
      {
        "value": "no",
        "expiry": 1736500985,
        "session": false,
        "http_only": false,
        "host_only": true,
        "secure": false,
        "same_site": "no_restriction"
      }
    ]
  },
  "cookielawinfo-checkbox-analytics": {
    "visit_id": 1,
    "name": "cookielawinfo-checkbox-analytics",
    "domain": "aslbi.piemonte.it",
    "path": "/",
    "first_party_domain": "",
    "label": 0,
    "cmp_origin": 0,
    "variable_data": [
      {
        "value": "no",
        "expiry": 1736500985,
        "session": false,
        "http_only": false,
        "host_only": true,
        "secure": false,
        "same_site": "no_restriction"
      }
    ]
  },
  "cookielawinfo-checkbox-advertisement": {
    "visit_id": 1,
    "name": "cookielawinfo-checkbox-advertisement",
    "domain": "aslbi.piemonte.it",
    "path": "/",
    "first_party_domain": "",
    "label": 0,
    "cmp_origin": 0,
    "variable_data": [
      {
        "value": "no",
        "expiry": 1736500985,
        "session": false,
        "http_only": false,
        "host_only": true,
        "secure": false,
        "same_site": "no_restriction"
      }
    ]
  },
  "cookielawinfo-checkbox-others": {
    "visit_id": 1,
    "name": "cookielawinfo-checkbox-others",
    "domain": "aslbi.piemonte.it",
    "path": "/",
    "first_party_domain": "",
    "label": 0,
    "cmp_origin": 0,
    "variable_data": [
      {
        "value": "no",
        "expiry": 1736500985,
        "session": false,
        "http_only": false,
        "host_only": true,
        "secure": false,
        "same_site": "no_restriction"
      }
    ]
  },
  "_pk_id.K23zWakp6X.11b9": {
    "visit_id": 1,
    "name": "_pk_id.K23zWakp6X.11b9",
    "domain": "aslbi.piemonte.it",
    "path": "/",
    "first_party_domain": "",
    "label": 0,
    "cmp_origin": 0,
    "variable_data": [
      {
        "value": "7e2a466def92cdda.1704964987.",
        "expiry": 1738920187,
        "session": false,
        "http_only": false,
        "host_only": true,
        "secure": false,
        "same_site": "lax"
      }
    ]
  },
  "_pk_ses.K23zWakp6X.11b9": {
    "visit_id": 1,
    "name": "_pk_ses.K23zWakp6X.11b9",
    "domain": "aslbi.piemonte.it",
    "path": "/",
    "first_party_domain": "",
    "label": 0,
    "cmp_origin": 0,
    "variable_data": [
      {
        "value": "1",
        "expiry": 1704966786,
        "session": false,
        "http_only": false,
        "host_only": true,
        "secure": false,
        "same_site": "lax"
      }
    ]
  },
  "cookielawinfo-checkbox-functional": {
    "visit_id": 1,
    "name": "cookielawinfo-checkbox-functional",
    "domain": "aslbi.piemonte.it",
    "path": "/",
    "first_party_domain": "",
    "label": 0,
    "cmp_origin": 0,
    "variable_data": [
      {
        "value": "yes",
        "expiry": 1736500988,
        "session": false,
        "http_only": false,
        "host_only": true,
        "secure": false,
        "same_site": "no_restriction"
      }
    ]
  },
  "cli_user_preference": {
    "visit_id": 1,
    "name": "cli_user_preference",
    "domain": "aslbi.piemonte.it",
    "path": "/",
    "first_party_domain": "",
    "label": 0,
    "cmp_origin": 0,
    "variable_data": [
      {
        "value": "it-checkbox-necessary-yes-checkbox-functional-yes-checkbox-performance-no-checkbox-analytics-no-checkbox-advertisement-no-checkbox-others-no",
        "expiry": 1736500988,
        "session": false,
        "http_only": false,
        "host_only": true,
        "secure": false,
        "same_site": "no_restriction"
      }
    ]
  },
  "CookieLawInfoConsent": {
    "visit_id": 1,
    "name": "CookieLawInfoConsent",
    "domain": "aslbi.piemonte.it",
    "path": "/",
    "first_party_domain": "",
    "label": 0,
    "cmp_origin": 0,
    "variable_data": [
      {
        "value": "eyJ2ZXIiOiIxIiwibmVjZXNzYXJ5IjoidHJ1ZSIsImZ1bmN0aW9uYWwiOiJ0cnVlIiwicGVyZm9ybWFuY2UiOiJmYWxzZSIsImFuYWx5dGljcyI6ImZhbHNlIiwiYWR2ZXJ0aXNlbWVudCI6ImZhbHNlIiwib3RoZXJzIjoiZmFsc2UifQ==",
        "expiry": 1736500988,
        "session": false,
        "http_only": false,
        "host_only": true,
        "secure": false,
        "same_site": "no_restriction"
      }
    ]
  }
}