{
  "_pk_id.jKq2vryqlV.3265": {
    "visit_id": 1,
    "name": "_pk_id.jKq2vryqlV.3265",
    "domain": "uniparthenope.it",
    "path": "/",
    "first_party_domain": "",
    "label": 0,
    "cmp_origin": 0,
    "variable_data": [
      {
        "value": "c177d6acb4946711.1704908903.",
        "expiry": 1738864103,
        "session": false,
        "http_only": false,
        "host_only": true,
        "secure": false,
        "same_site": "lax"
      }
    ]
  },
  "_pk_ses.jKq2vryqlV.3265": {
    "visit_id": 1,
    "name": "_pk_ses.jKq2vryqlV.3265",
    "domain": "uniparthenope.it",
    "path": "/",
    "first_party_domain": "",
    "label": 0,
    "cmp_origin": 0,
    "variable_data": [
      {
        "value": "1",
        "expiry": 1704910703,
        "session": false,
        "http_only": false,
        "host_only": true,
        "secure": false,
        "same_site": "lax"
      }
    ]
  }
}