{
  "MUID": {
    "visit_id": 1,
    "name": "MUID",
    "domain": ".bing.com",
    "path": "/",
    "first_party_domain": "",
    "label": 0,
    "cmp_origin": 0,
    "variable_data": [
      {
        "value": "32AB7AB1BC0E61C810776EB2BDEF603B",
        "expiry": 1738634293,
        "session": false,
        "http_only": false,
        "host_only": true,
        "secure": true,
        "same_site": "no_restriction"
      }
    ]
  },
  "_ga_QW473961LR": {
    "visit_id": 1,
    "name": "_ga_QW473961LR",
    "domain": ".agriturismo.it",
    "path": "/",
    "first_party_domain": "",
    "label": 0,
    "cmp_origin": 0,
    "variable_data": [
      {
        "value": "GS1.1.1704938293.1.0.1704938293.60.0.0",
        "expiry": 1739498293,
        "session": false,
        "http_only": false,
        "host_only": true,
        "secure": false,
        "same_site": "no_restriction"
      }
    ]
  },
  "_ga": {
    "visit_id": 1,
    "name": "_ga",
    "domain": ".agriturismo.it",
    "path": "/",
    "first_party_domain": "",
    "label": 0,
    "cmp_origin": 0,
    "variable_data": [
      {
        "value": "GA1.2.1206915283.1704938294",
        "expiry": 1739498294,
        "session": false,
        "http_only": false,
        "host_only": true,
        "secure": false,
        "same_site": "no_restriction"
      }
    ]
  },
  "_gid": {
    "visit_id": 1,
    "name": "_gid",
    "domain": ".agriturismo.it",
    "path": "/",
    "first_party_domain": "",
    "label": 0,
    "cmp_origin": 0,
    "variable_data": [
      {
        "value": "GA1.2.1391157385.1704938294",
        "expiry": 1705024694,
        "session": false,
        "http_only": false,
        "host_only": true,
        "secure": false,
        "same_site": "no_restriction"
      }
    ]
  },
  "_ga_4XWRPKX83W": {
    "visit_id": 1,
    "name": "_ga_4XWRPKX83W",
    "domain": ".agriturismo.it",
    "path": "/",
    "first_party_domain": "",
    "label": 0,
    "cmp_origin": 0,
    "variable_data": [
      {
        "value": "GS1.1.1704938294.1.0.1704938294.60.0.0",
        "expiry": 1739498294,
        "session": false,
        "http_only": false,
        "host_only": true,
        "secure": false,
        "same_site": "no_restriction"
      }
    ]
  },
  "_gat_gtag_UA_8889691_1": {
    "visit_id": 1,
    "name": "_gat_gtag_UA_8889691_1",
    "domain": ".agriturismo.it",
    "path": "/",
    "first_party_domain": "",
    "label": 0,
    "cmp_origin": 0,
    "variable_data": [
      {
        "value": "1",
        "expiry": 1704938354,
        "session": false,
        "http_only": false,
        "host_only": true,
        "secure": false,
        "same_site": "no_restriction"
      }
    ]
  },
  "IDE": {
    "visit_id": 1,
    "name": "IDE",
    "domain": ".doubleclick.net",
    "path": "/",
    "first_party_domain": "",
    "label": 0,
    "cmp_origin": 0,
    "variable_data": [
      {
        "value": "AHWqTUlVQHJI-fwsg9kKhWAdOmmhOCZgEkWPDatw0k-bBsu0oKKBnD520mMU1uG2CdY",
        "expiry": 1738634294,
        "session": false,
        "http_only": true,
        "host_only": true,
        "secure": true,
        "same_site": "no_restriction"
      }
    ]
  },
  "iperceptions.com": {
    "visit_id": 1,
    "name": "iperceptions.com",
    "domain": ".universal.iperceptions.com",
    "path": "/",
    "first_party_domain": "",
    "label": 0,
    "cmp_origin": 0,
    "variable_data": [
      {
        "value": "[{\"id\":\"acd95f53-5212-4635-a9b0-f65f7b6271fe\",\"history\":[],\"visitors\":[{\"id\":\"4997892235\",\"time\":\"2024-01-11T01:58:15.820Z\",\"host\":\"www.agriturismo.it\"}]}]",
        "expiry": 1712714296,
        "session": false,
        "http_only": false,
        "host_only": true,
        "secure": true,
        "same_site": "no_restriction"
      }
    ]
  },
  "CookieConsent": {
    "visit_id": 1,
    "name": "CookieConsent",
    "domain": "www.agriturismo.it",
    "path": "/",
    "first_party_domain": "",
    "label": 0,
    "cmp_origin": 0,
    "variable_data": [
      {
        "value": "{stamp:%27SlnEImH0O6iE3d1RYELJzmPxiKrhx/Xh80fHmAt6BNb3N9sebkJ3vw==%27%2Cnecessary:true%2Cpreferences:false%2Cstatistics:false%2Cmarketing:false%2Cmethod:%27explicit%27%2Cver:1%2Cutc:1704938299470%2Cregion:%27it%27}",
        "expiry": 1736560699,
        "session": false,
        "http_only": false,
        "host_only": true,
        "secure": true,
        "same_site": "no_restriction"
      }
    ]
  }
}